fwgen/__init__.py
fwgen/fwgen.py
fwgen/helpers.py
fwgen/version.py
fwgen/bin/__init__.py
fwgen/bin/fwgen.py
fwgen/doc/examples/config.yml
fwgen/doc/examples/fwgen.service
fwgen/etc/defaults.yml
fwgen-0.19.0.dist-info/LICENSE.txt
fwgen-0.19.0.dist-info/METADATA
fwgen-0.19.0.dist-info/WHEEL
fwgen-0.19.0.dist-info/entry_points.txt
fwgen-0.19.0.dist-info/top_level.txt
fwgen-0.19.0.dist-info/RECORD
