Metadata-Version: 2.1
Name: fwgen
Version: 0.19.0
Summary: A simple management framework for ip(6)tables based firewalls
Home-page: https://github.com/hkbakke/fwgen
Author: Hans-Kristian Bakke
License: MIT
Keywords: linux firewall iptables ip6tables ipset
Platform: UNKNOWN
Classifier: Development Status :: 5 - Production/Stable
Classifier: Intended Audience :: System Administrators
Classifier: Topic :: System :: Networking :: Firewalls
Classifier: Operating System :: POSIX :: Linux
Classifier: License :: OSI Approved :: MIT License
Classifier: Programming Language :: Python :: 3
Classifier: Programming Language :: Python :: 3.4
Classifier: Programming Language :: Python :: 3.5
Classifier: Programming Language :: Python :: 3.6
Classifier: Programming Language :: Python :: 3.7
Requires-Dist: pyyaml
Provides-Extra: test
Requires-Dist: pylint ; extra == 'test'
Requires-Dist: pytest ; extra == 'test'
Requires-Dist: pytest-cov ; extra == 'test'
